CHANGES.txt
LICENSE.txt
MANIFEST.in
README.txt
setup.py
js/__init__.py
js.jquery_datatables.egg-info/PKG-INFO
js.jquery_datatables.egg-info/SOURCES.txt
js.jquery_datatables.egg-info/dependency_links.txt
js.jquery_datatables.egg-info/entry_points.txt
js.jquery_datatables.egg-info/namespace_packages.txt
js.jquery_datatables.egg-info/not-zip-safe
js.jquery_datatables.egg-info/requires.txt
js.jquery_datatables.egg-info/top_level.txt
js/jquery_datatables/__init__.py
js/jquery_datatables/test_jquery_datatables.txt
js/jquery_datatables/resources/Contributing.md
js/jquery_datatables/resources/Readme.md
js/jquery_datatables/resources/license.txt
js/jquery_datatables/resources/extensions/AutoFill/Readme.txt
js/jquery_datatables/resources/extensions/AutoFill/css/dataTables.autoFill.css
js/jquery_datatables/resources/extensions/AutoFill/css/dataTables.autoFill.min.css
js/jquery_datatables/resources/extensions/AutoFill/images/filler.png
js/jquery_datatables/resources/extensions/AutoFill/js/dataTables.autoFill.js
js/jquery_datatables/resources/extensions/AutoFill/js/dataTables.autoFill.min.js
js/jquery_datatables/resources/extensions/ColReorder/License.txt
js/jquery_datatables/resources/extensions/ColReorder/Readme.md
js/jquery_datatables/resources/extensions/ColReorder/css/dataTables.colReorder.css
js/jquery_datatables/resources/extensions/ColReorder/css/dataTables.colReorder.min.css
js/jquery_datatables/resources/extensions/ColReorder/images/insert.png
js/jquery_datatables/resources/extensions/ColReorder/js/dataTables.colReorder.js
js/jquery_datatables/resources/extensions/ColReorder/js/dataTables.colReorder.min.js
js/jquery_datatables/resources/extensions/ColVis/License.txt
js/jquery_datatables/resources/extensions/ColVis/Readme.md
js/jquery_datatables/resources/extensions/ColVis/css/dataTables.colVis.css
js/jquery_datatables/resources/extensions/ColVis/css/dataTables.colVis.min.css
js/jquery_datatables/resources/extensions/ColVis/css/dataTables.colvis.jqueryui.css
js/jquery_datatables/resources/extensions/ColVis/js/dataTables.colVis.js
js/jquery_datatables/resources/extensions/ColVis/js/dataTables.colVis.min.js
js/jquery_datatables/resources/extensions/FixedColumns/License.txt
js/jquery_datatables/resources/extensions/FixedColumns/Readme.md
js/jquery_datatables/resources/extensions/FixedColumns/css/dataTables.fixedColumns.css
