Metadata-Version: 1.0
Name: js.jquery-datatables
Version: 1.10.7
Summary: Fanstatic packaging of jQuery Datatables
Home-page: UNKNOWN
Author: Fanstatic Developers
Author-email: fanstatic@googlegroups.com
License: BSD
Platform: UNKNOWN
